aiodatabase/__init__.py
aiodatabase/dataConnector.py
aiodatabase/database.py
aiodatabase/manager/__init__.py
aiodatabase/manager/configManager.py
aiodatabase/sqlite3/__init__.py
aiodatabase/sqlite3/sqlLoader.py
aiodatabase-1.0.0.dist-info/LICENSE
aiodatabase-1.0.0.dist-info/METADATA
aiodatabase-1.0.0.dist-info/WHEEL
aiodatabase-1.0.0.dist-info/top_level.txt
aiodatabase-1.0.0.dist-info/RECORD
